funny_random_name_generator-1.0.0.data/data/random_name_generator/adjectives.txt
funny_random_name_generator-1.0.0.data/data/random_name_generator/latin_adjectives.txt
funny_random_name_generator-1.0.0.data/data/random_name_generator/latin_nouns.txt
funny_random_name_generator-1.0.0.data/data/random_name_generator/nouns.txt
funny_random_name_generator-1.0.0.data/data/random_name_generator/sicilian_nouns.txt
funny_random_name_generator-1.0.0.dist-info/METADATA
funny_random_name_generator-1.0.0.dist-info/RECORD
funny_random_name_generator-1.0.0.dist-info/WHEEL
funny_random_name_generator-1.0.0.dist-info/top_level.txt
random_name_generator/__init__.py
random_name_generator/files/__init__.py
random_name_generator/files/adjectives.txt
random_name_generator/files/latin_adjectives.txt
random_name_generator/files/latin_nouns.txt
random_name_generator/files/nouns.txt
random_name_generator/files/sicilian_nouns.txt
random_name_generator/resources/__init__.py
random_name_generator/resources/name_generator.py
random_name_generator/resources/nouns.py
